Metadata-Version: 2.1
Name: nizzix
Version: 1.6
Summary: Simple package
Home-page: https://github.com/yashing2/import-nizzix
Author: yaz_v2
Author-email: discordyashing@gmail.com
Classifier: Environment :: Win32 (MS Windows)
Classifier: Natural Language :: French
Classifier: Operating System :: Microsoft :: Windows :: Windows 10
Classifier: Operating System :: Microsoft :: Windows :: Windows 11
Classifier: Programming Language :: Python :: 3.11
Classifier: Topic :: Internet :: Proxy Servers
Classifier: Topic :: System
Classifier: Topic :: System :: Logging
Requires-Python: >=3.11
License-File: LICENSE
Requires-Dist: cloudscraper==1.2.71
Requires-Dist: discord_interactions==0.4.0
Requires-Dist: psutil==6.1.0
Requires-Dist: pyttsx3==2.98
Requires-Dist: requests==2.32.3
Requires-Dist: win32security==2.1.0
Requires-Dist: wmi==1.5.1
